gc2/__init__.py
gc2/gc2.py
gc2/meta.py
gc2/sql.py
gc2_python_client-2022.8.1.dist-info/LICENSE
gc2_python_client-2022.8.1.dist-info/METADATA
gc2_python_client-2022.8.1.dist-info/WHEEL
gc2_python_client-2022.8.1.dist-info/top_level.txt
gc2_python_client-2022.8.1.dist-info/RECORD
