Metadata-Version: 2.1
Name: gc2-python-client
Version: 2022.8.1
Summary: Python client for GC2
Author-email: Martin Høgh <mh@mapcentia.com>
License: GNU GENERAL PUBLIC LICENSE
Project-URL: Homepage, https://github.com/mapcentia/gc2-python-client
Project-URL: Bug Tracker, https://github.com/mapcentia/gc2-python-client/issues
Classifier: Programming Language :: Python :: 3
Classifier: License :: OSI Approved :: MIT License
Classifier: Operating System :: OS Independent
Requires-Python: >=3.6
License-File: LICENSE
